pygaps/__init__.py
pygaps/_version.py
pygaps/logging.py
pygaps/characterisation/__init__.py
pygaps/characterisation/alphas_plots.py
pygaps/characterisation/area_bet.py
pygaps/characterisation/area_lang.py
pygaps/characterisation/dr_da_plots.py
pygaps/characterisation/enth_sorp_clapeyron.py
pygaps/characterisation/enth_sorp_initial.py
pygaps/characterisation/enth_sorp_whittaker.py
pygaps/characterisation/initial_henry.py
pygaps/characterisation/models_hk.py
pygaps/characterisation/models_kelvin.py
pygaps/characterisation/models_thickness.py
pygaps/characterisation/psd_kernel.py
pygaps/characterisation/psd_meso.py
pygaps/characterisation/psd_micro.py
pygaps/characterisation/t_plots.py
pygaps/cli/__init__.py
pygaps/cli/cli.py
pygaps/core/__init__.py
pygaps/core/adsorbate.py
pygaps/core/baseisotherm.py
pygaps/core/material.py
pygaps/core/modelisotherm.py
pygaps/core/pointisotherm.py
pygaps/data/__init__.py
pygaps/data/adsorbate_props.json
pygaps/data/adsorbates.json
pygaps/data/default.db
pygaps/data/kernels/DFT-N2-77K-carbon-slit.csv
pygaps/data/stdiso/Cabot BP280 carbon black.csv
pygaps/data/stdiso/LiChrospher Si-1000 silica.csv
pygaps/graphing/__init__.py
pygaps/graphing/calc_graphs.py
pygaps/graphing/iast_graphs.py
pygaps/graphing/isotherm_graphs.py
pygaps/graphing/labels.py
pygaps/graphing/model_graphs.py
pygaps/graphing/mpl_styles.py
pygaps/graphing/prediction_graphs.py
pygaps/modelling/__init__.py
pygaps/modelling/base_model.py
pygaps/modelling/bet.py
pygaps/modelling/chemiphysisorption.py
pygaps/modelling/da.py
pygaps/modelling/dr.py
pygaps/modelling/dslangmuir.py
pygaps/modelling/dstoth.py
pygaps/modelling/fhvst.py
pygaps/modelling/freundlich.py
pygaps/modelling/gab.py
pygaps/modelling/henry.py
pygaps/modelling/jensenseaton.py
pygaps/modelling/langmuir.py
pygaps/modelling/quadratic.py
pygaps/modelling/temkinapprox.py
pygaps/modelling/toth.py
pygaps/modelling/tslangmuir.py
pygaps/modelling/virial.py
pygaps/modelling/wvst.py
pygaps/parsing/__init__.py
pygaps-4.6.1.dist-info/AUTHORS.rst
pygaps-4.6.1.dist-info/LICENSE
pygaps-4.6.1.dist-info/METADATA
pygaps-4.6.1.dist-info/WHEEL
pygaps-4.6.1.dist-info/entry_points.txt
pygaps-4.6.1.dist-info/top_level.txt
pygaps-4.6.1.dist-info/zip-safe
pygaps-4.6.1.dist-info/RECORD
