Metadata-Version: 2.2
Name: pygaps
Version: 4.6.1
Summary: Framework for processing gas adsorption isotherms
Author-email: Paul Iacomi <mail@pauliacomi.com>
License: MIT License
Project-URL: Homepage, https://github.com/pauliacomi/pygaps
Project-URL: Repository, https://github.com/pauliacomi/pygaps.git
Project-URL: Documentation, https://pygaps.readthedocs.io
Keywords: adsorption,isotherm,characterization,processing,material
Classifier: Development Status :: 5 - Production/Stable
Classifier: Intended Audience :: Science/Research
Classifier: License :: OSI Approved :: MIT License
Classifier: Operating System :: OS Independent
Classifier: Programming Language :: Python :: 3.8
Classifier: Programming Language :: Python :: 3.9
Classifier: Programming Language :: Python :: 3.10
Classifier: Programming Language :: Python :: 3.11
Classifier: Programming Language :: Python :: 3.12
Classifier: Programming Language :: Python :: 3.13
Classifier: Topic :: Scientific/Engineering :: Chemistry
Classifier: Topic :: Scientific/Engineering :: Physics
Requires-Python: >=3.8
License-File: LICENSE
License-File: AUTHORS.rst
Requires-Dist: numpy>=1.16.5
Requires-Dist: scipy>=1.5.0
Requires-Dist: pandas>=1.1.0
Requires-Dist: matplotlib>=3.3.0
Requires-Dist: coolprop>=6.0.0; python_version < "3.13"
Requires-Dist: coolprop>=6.7.0; python_version >= "3.13"
Requires-Dist: adsorption-file-parser>=0.2.6
Requires-Dist: xlrd>=1.1
Requires-Dist: xlwt>=1.3
Requires-Dist: openpyxl
Requires-Dist: gemmi
Requires-Dist: requests
Requires-Dist: importlib_resources; python_version < "3.9"
Provides-Extra: all
Requires-Dist: pygaps[dev,docs,test]; extra == "all"
Provides-Extra: dev
Requires-Dist: pygaps[docs,test]; extra == "dev"
Requires-Dist: codecov; extra == "dev"
Requires-Dist: yapf; extra == "dev"
Requires-Dist: isort; extra == "dev"
Requires-Dist: pylint; extra == "dev"
Requires-Dist: flake8; extra == "dev"
Requires-Dist: flake8-pyproject; extra == "dev"
Requires-Dist: autopep8; extra == "dev"
Requires-Dist: pydocstyle; extra == "dev"
Requires-Dist: pygments; extra == "dev"
Requires-Dist: docutils; extra == "dev"
Provides-Extra: docs
Requires-Dist: pygments>=2.11; extra == "docs"
Requires-Dist: docutils>=0.11; extra == "docs"
Requires-Dist: doc8; extra == "docs"
Requires-Dist: pandoc; extra == "docs"
Requires-Dist: restructuredtext-lint; extra == "docs"
Requires-Dist: ipykernel; extra == "docs"
Requires-Dist: sphinx>=4.0; extra == "docs"
Requires-Dist: sphinx-copybutton; extra == "docs"
Requires-Dist: nbsphinx; extra == "docs"
Requires-Dist: furo; extra == "docs"
Provides-Extra: test
Requires-Dist: pytest>=6.0.0; extra == "test"
Requires-Dist: pytest-cov; extra == "test"
Requires-Dist: coverage[toml]; extra == "test"
Requires-Dist: nose; extra == "test"
